flai_sdk/__init__.py
flai_sdk/config.py
flai_sdk/config_cli.py
flai_sdk/utils.py
flai_sdk/api/__init__.py
flai_sdk/api/ai_models.py
flai_sdk/api/base.py
flai_sdk/api/cli_clients.py
flai_sdk/api/cli_executions.py
flai_sdk/api/client.py
flai_sdk/api/datasets.py
flai_sdk/api/downloads.py
flai_sdk/api/file_downloads.py
flai_sdk/api/flow_executions.py
flai_sdk/api/flow_templates.py
flai_sdk/api/flows.py
flai_sdk/api/opendata.py
flai_sdk/api/organizations.py
flai_sdk/api/project_dataset.py
flai_sdk/api/projects.py
flai_sdk/api/semantic_definition_schemas.py
flai_sdk/api/upload.py
flai_sdk/api/vectors.py
flai_sdk/cli/__init__.py
flai_sdk/cli/cli.py
flai_sdk/models/__init__.py
flai_sdk/models/ai_models.py
flai_sdk/models/ai_training_sessions.py
flai_sdk/models/base.py
flai_sdk/models/cli_clients.py
flai_sdk/models/cli_executions.py
flai_sdk/models/datasets.py
flai_sdk/models/datasource.py
flai_sdk/models/flow_executions.py
flai_sdk/models/flow_templates.py
flai_sdk/models/pointclouds.py
flai_sdk/models/project_dataset.py
flai_sdk/models/projects.py
flai_sdk/models/semantic_definition_schemas.py
flai_sdk/tools/download.py
flai_sdk/tools/fileinfo.py
flai_sdk/tools/utils.py
flai_sdk/tools/utils_api.py
flai_sdk-1.1.1.dist-info/licenses/LICENSE
flai_sdk-1.1.1.dist-info/METADATA
flai_sdk-1.1.1.dist-info/WHEEL
flai_sdk-1.1.1.dist-info/entry_points.txt
flai_sdk-1.1.1.dist-info/top_level.txt
flai_sdk-1.1.1.dist-info/RECORD
