Metadata-Version: 2.4
Name: flai-sdk
Version: 1.1.1
Summary: A command-line toolset for interacting with the Flai web app.
Author-email: "Flai d.o.o." <info@flai.ai>
License-Expression: MIT
Project-URL: Homepage, https://github.com/flai-ai/flai-sdk
Project-URL: Issues, https://github.com/flai-ai/flai-sdk/issues
Classifier: Development Status :: 5 - Production/Stable
Classifier: Intended Audience :: Developers
Classifier: Intended Audience :: Education
Classifier: Intended Audience :: Science/Research
Classifier: Operating System :: MacOS
Classifier: Operating System :: Microsoft :: Windows
Classifier: Operating System :: Unix
Classifier: Programming Language :: Python :: 3
Classifier: Programming Language :: Python :: Implementation :: PyPy
Classifier: Topic :: Scientific/Engineering :: Artificial Intelligence
Classifier: Topic :: Software Development
Classifier: Topic :: System :: Logging
Classifier: Topic :: System :: Monitoring
Requires-Python: >=3.7
License-File: LICENSE
Requires-Dist: requests
Requires-Dist: numpy
Requires-Dist: click
Requires-Dist: laspy
Requires-Dist: lazrs
Requires-Dist: boto3
Requires-Dist: GPUtil
Requires-Dist: psutil
Requires-Dist: tenacity
Requires-Dist: py-cpuinfo
Requires-Dist: pycryptodome
Requires-Dist: cryptography
Requires-Dist: xxhash
Requires-Dist: m2r2
Dynamic: license-file
